{
    "format_version": 1,
    "registry_version": "v1.0.12",
    "chips": {
        "esp32c6": {
            "name": "esp32c6",
            "arch": "riscv32",
            "compiler_prefix": "riscv32-esp-elf-",
            "description": "Espressif ESP32-C6 (RISC-V, 4MB Flash, WiFi 6, BLE 5)",
            "version": "1.1.0",
            "path": "chips/esp32c6",
            "verified": false,
            "sources": {
                "startup": "startup.c",
                "platform": "chip_platform.c",
                "config": "chip_config.h",
                "linker": "esp32c6_stage1.ld",
                "hardware": "hardware.json",
                "drivers": [
                    "drivers/uart/esp_uart_v1/console.c",
                    "drivers/flash/esp_rom_spi/flash.c",
                    "drivers/wdt/esp_rwdt_with_swd/wdt.c",
                    "drivers/rtc/esp_rtc_mem/confirm.c",
                    "drivers/clock/esp_systimer/reset_reason.c"
                ],
                "extra": [
                    "mock_efuse.c"
                ]
            },
            "includes": [
                "soc/esp/include",
                "arch/riscv32/include"
            ]
        }
    },
    "toolchains": {
        "riscv32-esp-elf": {
            "path": "toolchains/riscv32-esp-elf",
            "version": "1.0.0",
            "upstream_version": "13.2.0_20230928",
            "urls": {
                "darwin_amd64": "https://github.com/espressif/crosstool-NG/releases/download/esp-13.2.0_20230928/riscv32-esp-elf-13.2.0_20230928-x86_64-apple-darwin.tar.xz",
                "darwin_arm64": "https://github.com/espressif/crosstool-NG/releases/download/esp-13.2.0_20230928/riscv32-esp-elf-13.2.0_20230928-aarch64-apple-darwin.tar.xz",
                "linux_amd64": "https://github.com/espressif/crosstool-NG/releases/download/esp-13.2.0_20230928/riscv32-esp-elf-13.2.0_20230928-x86_64-linux-gnu.tar.xz",
                "windows_amd64": "https://github.com/espressif/crosstool-NG/releases/download/esp-13.2.0_20230928/riscv32-esp-elf-13.2.0_20230928-x86_64-w64-mingw32.zip"
            },
            "sha256": {
                "darwin_amd64": "e3b0c44298fc1c149afbf4c8996fb92427ae41e4649b934ca495991b7852b855",
                "darwin_arm64": "e3b0c44298fc1c149afbf4c8996fb92427ae41e4649b934ca495991b7852b855",
                "linux_amd64": "782feefe354500c5f968e8c91959651be3bdbbd7ae8a17affcee2b1bffcaad89",
                "windows_amd64": "1300a54505dc964fa9104482737152e669f4d880efc1d54057378d9e6910ae1e"
            }
        }
    },
    "archs": {
        "riscv32": {
            "name": "riscv32",
            "path": "arch/riscv32",
            "version": "1.0.0",
            "description": "RISC-V 32-bit Architecture Support"
        }
    },
    "drivers": {
        "esp_rom_spi": {
            "name": "esp_rom_spi",
            "path": "drivers/flash/esp_rom_spi",
            "version": "1.0.0",
            "description": "ESP32 SPI Flash Driver via ROM pointers",
            "category": "flash"
        },
        "esp_rtc_mem": {
            "name": "esp_rtc_mem",
            "path": "drivers/rtc/esp_rtc_mem",
            "version": "1.0.0",
            "description": "ESP32 RTC LP_RAM Confirm Nonce Storage",
            "category": "rtc"
        },
        "esp_rwdt_with_swd": {
            "name": "esp_rwdt_with_swd",
            "path": "drivers/wdt/esp_rwdt_with_swd",
            "version": "1.0.0",
            "description": "ESP32 Regular Watchdog Timer (TIMG) with SWD sterilization",
            "category": "wdt"
        },
        "esp_systimer": {
            "name": "esp_systimer",
            "path": "drivers/clock/esp_systimer",
            "version": "1.0.0",
            "description": "ESP32 System Reset Reason via RTC_CNTL",
            "category": "clock"
        },
        "esp_uart_v1": {
            "name": "esp_uart_v1",
            "path": "drivers/uart/esp_uart_v1",
            "version": "1.0.0",
            "description": "ESP32 UART0 Console Driver",
            "category": "uart"
        }
    },
    "integrations": {
        "baremetal": {
            "name": "baremetal",
            "path": "integrations/baremetal",
            "version": "1.0.0",
            "description": "Baremetal Integration Hooks"
        },
        "espidf": {
            "name": "espidf",
            "path": "integrations/espidf",
            "version": "1.0.0",
            "description": "ESP-IDF Integration Hooks"
        },
        "zephyr": {
            "name": "zephyr",
            "path": "integrations/zephyr",
            "version": "1.0.0",
            "description": "Zephyr RTOS Integration Hooks"
        }
    }
}
